{
  "cookies": [
    {
      "name": "hubspotutk",
      "value": "00a193e86e29faca98a3b4d55556ad94",
      "domain": ".get-diamonds.com",
      "path": "/",
      "expires": 1777458682,
      "httpOnly": false,
      "secure": false,
      "sameSite": "Lax"
    },
    {
      "name": "__hssrc",
      "value": "1",
      "domain": ".get-diamonds.com",
      "path": "/",
      "expires": -1,
      "httpOnly": false,
      "secure": false,
      "sameSite": "Lax"
    },
    {
      "name": "_gid",
      "value": "GA1.2.641445472.1761903839",
      "domain": ".get-diamonds.com",
      "path": "/",
      "expires": 1761993080,
      "httpOnly": false,
      "secure": false,
      "sameSite": "Lax"
    },
    {
      "name": "__hstc",
      "value": "15936361.00a193e86e29faca98a3b4d55556ad94.1761032595908.1761206174884.1761903840036.3",
      "domain": ".get-diamonds.com",
      "path": "/",
      "expires": 1777458682,
      "httpOnly": false,
      "secure": false,
      "sameSite": "Lax"
    },
    {
      "name": "_cfuvid",
      "value": "o4k81WhsRRhLagE40Y_NPpgxwhIJ3R142LCoBcKCXY8-1761903844201-0.0.1.1-604800000",
      "domain": ".hubspot.com",
      "path": "/",
      "expires": -1,
      "httpOnly": true,
      "secure": true,
      "sameSite": "None"
    },
    {
      "name": "__cf_bm",
      "value": "evC8D8SkIW5J9hhEtHbZ4AG012IAS4a2PlfLKOxlHvk-1761906649-1.0.1.1-_spDeiIlyIJrQc20Gtk4OnvOjp4tyFpm.hrvg4.hBV55Iw_ZO5PhMhHd7.JQgySW052Nnr7VRsrnIBwYW6h8sFmoTbuFWKOKsPtCWWokJHU",
      "domain": ".hs-scripts.com",
      "path": "/",
      "expires": 1761908448.261567,
      "httpOnly": true,
      "secure": true,
      "sameSite": "None"
    },
    {
      "name": "_gat_gtag_UA_162907696_1",
      "value": "1",
      "domain": ".get-diamonds.com",
      "path": "/",
      "expires": 1761906708,
      "httpOnly": false,
      "secure": false,
      "sameSite": "Lax"
    },
    {
      "name": "__cf_bm",
      "value": "gU77zLbXJhXKlydsFZW3xnD800J58BosfXE9Ql6Svf4-1761906651-1.0.1.1-Y_qlsm1R9bpGvHhO3qVMNdy44mWrSGPM8ZaO3.9dfonugqXQkHBc_I5EItfEZBPzDYgC4ixnt9fabeVW7YSpQHXI4sxUdbEBp1UyjlZDjJ8",
      "domain": ".hs-analytics.net",
      "path": "/",
      "expires": 1761908449.667401,
      "httpOnly": true,
      "secure": true,
      "sameSite": "None"
    },
    {
      "name": "__cf_bm",
      "value": "fpOWoRudAoaJdVYSaYpVYlVwspICEvUF96FTYwPeesI-1761906651-1.0.1.1-m6tIUbEssk2K4Kf1u19jhukrwmp3lKyFBG1jCv4yX6E2VHuCnSBlrZ0GnuaBFhChBD9ttMbjeSG8MW7xpDlWKJ5YaW51n1ZhxL67eDF2At8",
      "domain": ".usemessages.com",
      "path": "/",
      "expires": 1761908449.68395,
      "httpOnly": true,
      "secure": true,
      "sameSite": "None"
    },
    {
      "name": "__cf_bm",
      "value": "90ke0hGOBioE0z8JNx7_2gVEjf6y9HycAkV2fAJ2qZc-1761906651-1.0.1.1-u_gpw69msjkzI50p1Ia2T3k5rvM3ffMDSh4VlQLzhLFyGiZ_tYteU7OzM1xRtbn0fnlYHvoYlFW3CS95zjmqhCZEYBTbTZ393VSAtA6RMR0",
      "domain": ".hs-banner.com",
      "path": "/",
      "expires": 1761908449.686265,
      "httpOnly": true,
      "secure": true,
      "sameSite": "None"
    },
    {
      "name": "__cf_bm",
      "value": "FxZDQfPNeWnDrZc3RsPTldCRNLB_z6ui4YKupdfEIOY-1761906652-1.0.1.1-TH6zKagx30kHZcoOiInbU3hbGEth09wLI3i_tetvKP5kn9iU.KLbXvY2PpzhMDYRmNlAvgk7SeJxKXe5xCe4l26QYw6pehjg0Rziwhed9nU",
      "domain": ".hubspot.com",
      "path": "/",
      "expires": 1761908451.214334,
      "httpOnly": true,
      "secure": true,
      "sameSite": "None"
    },
    {
      "name": "_ga",
      "value": "GA1.1.1921857962.1761032595",
      "domain": ".get-diamonds.com",
      "path": "/",
      "expires": 1796466680.320852,
      "httpOnly": false,
      "secure": false,
      "sameSite": "Lax"
    },
    {
      "name": "ph_phc_YeerX4y8IIbjKqclRhIvrB9EYgpf5U8jcZTnM8lOl6g_posthog",
      "value": "%7B%22distinct_id%22%3A%22019a05b8-e031-7b89-9850-22761353e4a3%22%2C%22%24sesid%22%3A%5B1761906680812%2C%22019a39a7-0787-7bf7-82c2-cdab91f94147%22%2C1761903839111%5D%7D",
      "domain": ".get-diamonds.com",
      "path": "/",
      "expires": 1793442681,
      "httpOnly": false,
      "secure": true,
      "sameSite": "Lax"
    },
    {
      "name": "__hssc",
      "value": "15936361.15.1761903840036",
      "domain": ".get-diamonds.com",
      "path": "/",
      "expires": 1761908482,
      "httpOnly": false,
      "secure": false,
      "sameSite": "Lax"
    },
    {
      "name": "_ga_CX8SYCQFGH",
      "value": "GS2.1.s1761903839$o3$g1$t1761906682$j26$l0$h0",
      "domain": ".get-diamonds.com",
      "path": "/",
      "expires": 1796466682.297732,
      "httpOnly": false,
      "secure": false,
      "sameSite": "Lax"
    }
  ],
  "origins": [
    {
      "origin": "https://stg.app.get-diamonds.com",
      "localStorage": [
        {
          "name": "token",
          "value": "eyJhbGciOiJIUzI1NiIsInR5cCI6IkpXVCJ9.eyJ1c2VySWQiOiI2ODRmYWQzOGYwMTkxMzU3ZWRkNGU2ODgiLCJpYXQiOjE3NjE5MDY2ODQsImV4cCI6MTc2MjA3OTQ4NH0.oUpAUvSrmeAa5rSCVttnGeLGkVY9NmtoZZkabSL_n7w"
        },
        {
          "name": "user",
          "value": "{\"user\":{\"contactMethods\":{\"email\":{\"enabled\":true,\"value\":\"mussadiq+4@faba.naibme.com\"},\"phone\":{\"enabled\":false,\"value\":\"+923164099602\"},\"sms\":{\"enabled\":false},\"whatsapp\":{\"enabled\":false},\"telegram\":{\"enabled\":false},\"wechat\":{\"enabled\":false}},\"bourseMembership\":{\"isBourseMember\":true,\"interestedInMembership\":false,\"showOnProfile\":true,\"accessTradingPage\":true,\"selectedBourses\":[{\"isBourseAdmin\":true,\"_id\":\"6887652bb78bfd001288dc75\",\"bourse\":\"6839bc7b23a0407833dc899d\",\"membershipNumber\":\"Shanghai-1\"},{\"isBourseAdmin\":false,\"_id\":\"6887652bb78bfd001288dc76\",\"bourse\":\"6839bc7b23a0407833dc8988\",\"membershipNumber\":\"5555\"},{\"isBourseAdmin\":false,\"_id\":\"6887652bb78bfd001288dc77\",\"bourse\":\"6839bc7b23a0407833dc89a0\",\"membershipNumber\":\"tokyo\"},{\"isBourseAdmin\":false,\"_id\":\"6887652bb78bfd001288dc78\",\"bourse\":\"6839bc7b23a0407833dc8998\",\"membershipNumber\":\"55\"},{\"isBourseAdmin\":false,\"_id\":\"6887652bb78bfd001288dc79\",\"bourse\":\"6839bc7b23a0407833dc8999\",\"membershipNumber\":\"55\"},{\"isBourseAdmin\":false,\"_id\":\"6887652bb78bfd001288dc7a\",\"bourse\":\"6839bc7b23a0407833dc899f\",\"membershipNumber\":\"55\"},{\"isBourseAdmin\":false,\"_id\":\"6887652bb78bfd001288dc7b\",\"bourse\":\"6839bc7b23a0407833dc8993\",\"membershipNumber\":\"5\"},{\"isBourseAdmin\":false,\"_id\":\"6887652bb78bfd001288dc7c\",\"bourse\":\"6839bc7b23a0407833dc8991\",\"membershipNumber\":\"88\"}]},\"addresses\":[],\"roles\":[\"user\",\"admin\",\"bourse-admin\"],\"wishlist\":[],\"favoriteMembers\":[],\"isSupplier\":false,\"accountType\":\"dealer\",\"approvedDplAml\":false,\"subscriptionId\":\"\",\"planId\":\"\",\"ydUserId\":\"402\",\"emailVerifiedAt\":\"2025-06-16T05:42:03.121Z\",\"lastLoginAt\":\"2025-10-31T10:31:24.549Z\",\"subscriptions\":[\"689b26d5f287a900121eac85\",\"689b36b66996fc0012d626bf\",\"689b379973e3e400114d4339\",\"689c3c357a957f0012185fb6\",\"68ede79b79a0390013e10b05\"],\"_id\":\"684fad38f0191357edd4e688\",\"firstName\":\"Mussadiq\",\"lastName\":\"Hussain\",\"email\":\"mussadiq@faba.naibme.com\",\"companyName\":\"company_hubspotss\",\"phoneNumber\":\"+923164099602\",\"company\":{\"companyInformation\":{\"companyDescription\":\"hubspot\"},\"sftpCredentials\":{\"privateKeys\":[\"-----BEGIN OPENSSH PRIVATE KEY-----\\nb3BlbnNzaC1rZXktdjEAAAAABG5vbmUAAAAEbm9uZQAAAAAAAAABAAAAMwAAAAtzc2gtZW\\nQyNTUxOQAAACAJleY466/dFuRXoII2OQOAsw0gtmIyNwMOTqlmPb4dcQAAAJAa2R2eGtkd\\nngAAAAtzc2gtZWQyNTUxOQAAACAJleY466/dFuRXoII2OQOAsw0gtmIyNwMOTqlmPb4dcQ\\nAAAECoXAv6geiEUaclhJxZZS3S5MIoxg2aZYCuZlc1xtdkBgmV5jjrr90W5FeggjY5A4Cz\\nDSC2YjI3Aw5OqWY9vh1xAAAACSh1bm5hbWVkKQECAwQ=\\n-----END OPENSSH PRIVATE KEY-----\\n\"],\"_id\":\"689308557ca844001359e3bd\",\"userName\":\"mussadiq.faba.naibme.com\"},\"isMarketplace\":false,\"publishApproval\":false,\"isSupplier\":false,\"amlStatus\":\"pending\",\"isSubscribed\":false,\"_id\":\"684fad38f0191357edd4e685\",\"name\":\"company_hubspots\",\"aml\":{\"business\":{\"businessType\":\"Independent Jeweler\",\"companyAddress\":\"Lahore\",\"companyCity\":\"Lahore\",\"companyCountry\":\"Pakistan\",\"companyDate\":\"2025-07-06T19:00:00.000Z\",\"companyEmailAddress\":\"mussadiq+4@faba.naibme.com\",\"companyName\":\"company_hubspots\",\"companyPhone\":\"+923164545698\",\"companyState\":\"Pak\",\"companyWebsiteLink\":\"https://stg.app get-diamonds\",\"companyZip\":\"54000_test_hubspot\",\"registrationNumber\":\"12345_test_hubspot\",\"companyLogo\":\"https://get-diamonds-staging-bucket.s3.ap-southeast-1.amazonaws.com/company-logos/1750052152154-logo.webp\",\"businessDocuments\":[\"https://get-diamonds-staging-bucket.s3.ap-southeast-1.amazonaws.com/business-documents/1751956927900-document-1.pdf\"]}},\"ftpCredentials\":{\"pubkeyAdded\":true,\"_id\":\"684fad38f0191357edd4e686\",\"username\":\"zg4b5oQ7\",\"password\":\"bLkgf6_416\",\"ftpUserId\":1078},\"locationInformation\":[],\"createdAt\":\"2025-06-16T05:35:52.295Z\",\"updatedAt\":\"2025-10-15T11:29:42.240Z\",\"__v\":5},\"updatedAt\":\"2025-10-31T10:31:24.550Z\",\"createdAt\":\"2025-06-16T05:35:52.553Z\",\"__v\":14,\"addOns\":[],\"stripeCustomerId\":\"cus_SqyNNGDxN9aMDa\",\"defaultPaymentMethodId\":\"pm_1RvHohEORrerIbvgxvHFRpF7\"}}"
        },
        {
          "name": "refresh",
          "value": "eyJhbGciOiJIUzI1NiIsInR5cCI6IkpXVCJ9.eyJ1c2VySWQiOiI2ODRmYWQzOGYwMTkxMzU3ZWRkNGU2ODgiLCJpYXQiOjE3NjE5MDY2ODQsImV4cCI6MTc2MjUxMTQ4NH0.KhlTVtfHp8ktUi_ZZOM14x7WTr9-nn4OiTYmM1obCLc"
        },
        {
          "name": "ph_phc_YeerX4y8IIbjKqclRhIvrB9EYgpf5U8jcZTnM8lOl6g_posthog",
          "value": "{\"distinct_id\":\"019a05b8-e031-7b89-9850-22761353e4a3\",\"$sesid\":[1761906680812,\"019a39a7-0787-7bf7-82c2-cdab91f94147\",1761903839111],\"$initialization_time\":\"2025-10-31T10:31:20.811Z\",\"$configured_session_timeout_ms\":1800000,\"$session_recording_enabled_server_side\":false,\"$session_recording_network_payload_capture\":{\"capturePerformance\":false},\"$session_recording_canvas_recording\":{},\"$replay_sample_rate\":null,\"$replay_minimum_duration\":null,\"$autocapture_disabled_server_side\":false,\"$heatmaps_enabled_server_side\":false,\"$web_vitals_enabled_server_side\":false,\"$exception_capture_enabled_server_side\":false,\"$error_tracking_suppression_rules\":[],\"$dead_clicks_enabled_server_side\":false,\"$active_feature_flags\":[],\"$enabled_feature_flags\":{},\"$feature_flag_payloads\":{},\"$feature_flag_details\":{},\"$feature_flag_request_id\":\"1323a6ac-069a-48c0-a249-9215d51014c9\"}"
        }
      ]
    }
  ]
}